xyz_lbstracker/__init__.py
xyz_lbstracker/admin.py
xyz_lbstracker/apis.py
xyz_lbstracker/apps.py
xyz_lbstracker/choices.py
xyz_lbstracker/helper.py
xyz_lbstracker/models.py
xyz_lbstracker/receivers.py
xyz_lbstracker/serializers.py
xyz_lbstracker/signals.py
xyz_lbstracker/migrations/0001_initial.py
xyz_lbstracker/migrations/0002_auto_20211128_1446.py
xyz_lbstracker/migrations/0002_auto_20211208_0743.py
xyz_lbstracker/migrations/0003_location_method.py
xyz_lbstracker/migrations/__init__.py
xyz_lbstracker-0.1.4.dist-info/DESCRIPTION.rst
xyz_lbstracker-0.1.4.dist-info/METADATA
xyz_lbstracker-0.1.4.dist-info/RECORD
xyz_lbstracker-0.1.4.dist-info/WHEEL
xyz_lbstracker-0.1.4.dist-info/metadata.json
xyz_lbstracker-0.1.4.dist-info/top_level.txt
